jerelyn/__init__.py
jerelyn/jeje.py
jerelyn-0.1.6.dist-info/DESCRIPTION.rst
jerelyn-0.1.6.dist-info/METADATA
jerelyn-0.1.6.dist-info/RECORD
jerelyn-0.1.6.dist-info/WHEEL
jerelyn-0.1.6.dist-info/metadata.json
jerelyn-0.1.6.dist-info/top_level.txt
