Metadata-Version: 2.0
Name: jerelyn
Version: 0.1.6
Summary: An English/Filipino to Jejemon-speak translator
Home-page: https://github.com/hadrianpaulo/jerelyn
Author: Hadrian Paulo Lim
Author-email: hadrianpaulo@gmail.com
License: Apache2
Platform: UNKNOWN
Classifier: Development Status :: 2 - Pre-Alpha
Classifier: Intended Audience :: End Users/Desktop
Classifier: License :: OSI Approved :: Apache Software License
Classifier: Programming Language :: Python :: 3
